fraccalc/__init__.py
fraccalc/basic.py
fraccalc/analytic/__init__.py
fraccalc/analytic/functions.py
fraccalc/analytic/semi.py
fraccalc/numeric/__init__.py
fraccalc/numeric/diffintegral.py
fraccalc-0.0.4.dist-info/LICENSE.txt
fraccalc-0.0.4.dist-info/METADATA
fraccalc-0.0.4.dist-info/WHEEL
fraccalc-0.0.4.dist-info/top_level.txt
fraccalc-0.0.4.dist-info/RECORD
