Metadata-Version: 2.1
Name: fraccalc
Version: 0.0.4
Summary: Python supports for fractional calculus.
Home-page: https://github.com/JerryALee/fraccalc
Author: Chengrui Li
Author-email: cnlichengrui@foxmail.com
License: MIT
Platform: UNKNOWN
Classifier: License :: OSI Approved :: MIT License
Classifier: Programming Language :: Python
Classifier: Programming Language :: Python :: 3
Classifier: Programming Language :: Python :: 3.6
Classifier: Programming Language :: Python :: Implementation :: CPython
Classifier: Programming Language :: Python :: Implementation :: PyPy
Requires-Python: >=3.6.0
Requires-Dist: numpy
